featomic/torch/__init__.py
featomic/torch/_build_versions.py
featomic/torch/_c_lib.py
featomic/torch/calculator_base.py
featomic/torch/calculators.py
featomic/torch/clebsch_gordan.py
featomic/torch/system.py
featomic/torch/utils.py
featomic/torch/torch-2.3/include/featomic/torch.hpp
featomic/torch/torch-2.3/include/featomic/torch/autograd.hpp
featomic/torch/torch-2.3/include/featomic/torch/calculator.hpp
featomic/torch/torch-2.3/include/featomic/torch/exports.h
featomic/torch/torch-2.3/include/featomic/torch/system.hpp
featomic/torch/torch-2.3/lib/libfeatomic_torch.so
featomic/torch/torch-2.3/lib/cmake/featomic_torch/featomic_torch-config-version.cmake
featomic/torch/torch-2.3/lib/cmake/featomic_torch/featomic_torch-config.cmake
featomic/torch/torch-2.3/lib/cmake/featomic_torch/featomic_torch-targets-release.cmake
featomic/torch/torch-2.3/lib/cmake/featomic_torch/featomic_torch-targets.cmake
featomic/torch/torch-2.4/include/featomic/torch.hpp
featomic/torch/torch-2.4/include/featomic/torch/autograd.hpp
featomic/torch/torch-2.4/include/featomic/torch/calculator.hpp
featomic/torch/torch-2.4/include/featomic/torch/exports.h
featomic/torch/torch-2.4/include/featomic/torch/system.hpp
featomic/torch/torch-2.4/lib/libfeatomic_torch.so
featomic/torch/torch-2.4/lib/cmake/featomic_torch/featomic_torch-config-version.cmake
featomic/torch/torch-2.4/lib/cmake/featomic_torch/featomic_torch-config.cmake
featomic/torch/torch-2.4/lib/cmake/featomic_torch/featomic_torch-targets-release.cmake
featomic/torch/torch-2.4/lib/cmake/featomic_torch/featomic_torch-targets.cmake
featomic/torch/torch-2.5/include/featomic/torch.hpp
featomic/torch/torch-2.5/include/featomic/torch/autograd.hpp
featomic/torch/torch-2.5/include/featomic/torch/calculator.hpp
featomic/torch/torch-2.5/include/featomic/torch/exports.h
featomic/torch/torch-2.5/include/featomic/torch/system.hpp
featomic/torch/torch-2.5/lib/libfeatomic_torch.so
featomic_torch-0.7.2.dist-info/licenses/AUTHORS
featomic_torch-0.7.2.dist-info/licenses/LICENSE
featomic_torch-0.7.2.dist-info/sboms/auditwheel.cdx.json
featomic_torch-0.7.2.dist-info/METADATA
featomic_torch-0.7.2.dist-info/WHEEL
featomic_torch-0.7.2.dist-info/top_level.txt
featomic_torch-0.7.2.dist-info/RECORD
