Metadata-Version: 2.4
Name: featomic-torch
Version: 0.7.2
Summary: TorchScript bindings to featomic
Author: Guillaume Fraux, Philip Loche, Sergei Kliavinek, Kevin Kazuki Huguenin-Dumittan, Davide Tisi, Alexander Goscinski
License-Expression: BSD-3-Clause
Project-URL: homepage, https://metatensor.github.io/featomic/latest/
Project-URL: documentation, https://metatensor.github.io/featomic/latest/
Project-URL: repository, https://github.com/metatensor/featomic
Keywords: computational science,machine learning,molecular modeling,atomistic representations,torch
Classifier: Development Status :: 4 - Beta
Classifier: Intended Audience :: Science/Research
Classifier: Operating System :: POSIX
Classifier: Operating System :: MacOS :: MacOS X
Classifier: Operating System :: Microsoft :: Windows
Classifier: Programming Language :: Python
Classifier: Programming Language :: Python :: 3
Classifier: Topic :: Scientific/Engineering
Classifier: Topic :: Scientific/Engineering :: Bio-Informatics
Classifier: Topic :: Scientific/Engineering :: Chemistry
Classifier: Topic :: Scientific/Engineering :: Physics
Classifier: Topic :: Software Development :: Libraries
Classifier: Topic :: Software Development :: Libraries :: Python Modules
Requires-Python: >=3.10
License-File: LICENSE
License-File: AUTHORS
Requires-Dist: torch>=2.1
Requires-Dist: metatensor-torch<0.9,>=0.8.0
Requires-Dist: metatomic-torch<0.2,>=0.1.4
Requires-Dist: featomic<0.7,>=0.6.3
Dynamic: author
Dynamic: license-file
Dynamic: requires-dist
